Single Port RAM.srcs/sources_1/new/module_design.v
`timescale 1ns / 1ps
//////////////////////////////////////////////////////////////////////////////////
// Company: 
// Engineer: 
// 
// Create Date: 30.03.2024 17:08:27
// Design Name: 
// Module Name: module_design
// Project Name: 
// Target Devices: 
// Tool Versions: 
// Description: 
// 
// Dependencies: 
// 
// Revision:
// Revision 0.01 - File Created
// Additional Comments:
// 
//////////////////////////////////////////////////////////////////////////////////


// Single Port RAM module design

module module_design(
  input [7:0] data, //input data
  input [5:0] addr, //address
  input we, //write enable
  input clk, //clk
  output [7:0] q //output data
);
  
  reg [7:0] ram [63:0]; //8*64 bit ram
  reg [5:0] addr_reg; //address register
 
  always @ (posedge clk)
    begin
      if(we)
        ram[addr] <= data;
      else
        addr_reg <= addr; 
    end
 
  assign q = ram[addr_reg];
  
endmodule

Single Port RAM.srcs/sim_1/new/module_testbench.v
`timescale 1ns / 1ps
//////////////////////////////////////////////////////////////////////////////////
// Company: 
// Engineer: 
// 
// Create Date: 30.03.2024 17:09:29
// Design Name: 
// Module Name: module_testbench
// Project Name: 
// Target Devices: 
// Tool Versions: 
// Description: 
// 
// Dependencies: 
// 
// Revision:
// Revision 0.01 - File Created
// Additional Comments:
// 
//////////////////////////////////////////////////////////////////////////////////


// Single Port RAM testbench

module module_testbench;
  reg [7:0] data; //input data
  reg [5:0] addr; //address
  reg we; //write enable
  reg clk; //clk
  wire [7:0] q; //output data 	
  
  module_design utt1(
    .data(data),
    .addr(addr),
    .we(we),
    .clk(clk),
    .q(q)
  );
  
  initial
    begin
      $dumpfile("dump.vcd");
      $dumpvars(1, module_testbench);       
      
      clk=1'b1;
      forever #5 clk = ~clk;
    end
  
  initial
    begin
      data = 8'h01;
      addr = 5'd0;
      we = 1'b1;
      #10;
           
	  data = 8'h02;
      addr = 5'd1;     
      #10;
      
      data = 8'h03;
      addr = 5'd2;     
      #10;
      
      addr = 5'd0;
      we = 1'b0;
      #10;
      
      addr = 5'd1;
      #10;
      
      addr = 5'd2;
      #10;
      
      data = 8'h04;
      addr = 5'd1;
      we = 1'b1;
      #10;
      
      addr = 5'd1;
      we = 1'b0;
      #10;
      
      addr = 5'd3;
      #10;
    end
  
  initial
    #90 $stop;
  
endmodule

Single Port RAM.sim/sim_1/behav/xsim/dump.vcd
$date
   Sat Mar 30 17:11:28 2024
$end

$version
  2023.2
  $dumpfile ("dump.vcd") 
$end

$timescale
  1ps
$end

$scope module module_testbench $end
$var reg 8 ! data [7:0] $end
$var reg 6 " addr [5:0] $end
$var reg 1 # we $end
$var reg 1 $ clk $end
$var wire 8 % q [7:0] $end
$upscope $end
$scope module glbl $end
$upscope $end
$enddefinitions $end

#0
$dumpvars
b1 !
b0 "
1#
1$
bx %
$end

#5000
0$

#10000
b10 !
b1 "
1$

#15000
0$

#20000
b11 !
b10 "
1$

#25000
0$

#30000
b0 "
0#
1$
b1 %

#35000
0$

#40000
b1 "
1$
b10 %

#45000
0$

#50000
b10 "
1$
b11 %

#55000
0$

#60000
b100 !
b1 "
1#
1$

#65000
0$

#70000
0#
1$
b100 %

#75000
0$

#80000
b11 "
1$
bx %

